{
  "generated_at": "2026-06-10 07:53:56",
  "source": "Open-Meteo",
  "regions": {
    "north": {
      "name": "华北/东北",
      "city": "Beijing",
      "days": [
        {
          "date": "2026-06-10",
          "code": 55,
          "weather": "中雨",
          "temp_max": 28.3,
          "temp_min": 17.9,
          "precipitation": 1.3,
          "wind": 14.5,
          "risk_score": 0,
          "signal": "天气整体平稳，户外与亲子活动具备恢复基础"
        },
        {
          "date": "2026-06-11",
          "code": 2,
          "weather": "多云",
          "temp_max": 31.9,
          "temp_min": 17.2,
          "precipitation": 0.0,
          "wind": 13.9,
          "risk_score": 20,
          "signal": "气温偏高，防晒、短裤、轻薄T恤需求提升"
        },
        {
          "date": "2026-06-12",
          "code": 3,
          "weather": "阴",
          "temp_max": 34.1,
          "temp_min": 21.9,
          "precipitation": 0.0,
          "wind": 14.7,
          "risk_score": 20,
          "signal": "气温偏高，防晒、短裤、轻薄T恤需求提升"
        }
      ],
      "risk_score": 20,
      "signal": "天气整体平稳，户外与亲子活动具备恢复基础"
    },
    "east": {
      "name": "华中/华东",
      "city": "Shanghai",
      "days": [
        {
          "date": "2026-06-10",
          "code": 3,
          "weather": "阴",
          "temp_max": 30.0,
          "temp_min": 15.3,
          "precipitation": 0.0,
          "wind": 10.4,
          "risk_score": 20,
          "signal": "气温偏高，防晒、短裤、轻薄T恤需求提升"
        },
        {
          "date": "2026-06-11",
          "code": 3,
          "weather": "阴",
          "temp_max": 33.5,
          "temp_min": 19.3,
          "precipitation": 0.0,
          "wind": 15.0,
          "risk_score": 20,
          "signal": "气温偏高，防晒、短裤、轻薄T恤需求提升"
        },
        {
          "date": "2026-06-12",
          "code": 3,
          "weather": "阴",
          "temp_max": 32.5,
          "temp_min": 21.4,
          "precipitation": 0.0,
          "wind": 13.9,
          "risk_score": 20,
          "signal": "气温偏高，防晒、短裤、轻薄T恤需求提升"
        }
      ],
      "risk_score": 20,
      "signal": "气温偏高，防晒、短裤、轻薄T恤需求提升"
    },
    "south": {
      "name": "华南",
      "city": "Guangzhou",
      "days": [
        {
          "date": "2026-06-10",
          "code": 3,
          "weather": "阴",
          "temp_max": 29.9,
          "temp_min": 22.1,
          "precipitation": 0.0,
          "wind": 11.0,
          "risk_score": 0,
          "signal": "天气整体平稳，户外与亲子活动具备恢复基础"
        },
        {
          "date": "2026-06-11",
          "code": 51,
          "weather": "小雨",
          "temp_max": 30.8,
          "temp_min": 24.0,
          "precipitation": 0.2,
          "wind": 10.2,
          "risk_score": 20,
          "signal": "气温偏高，防晒、短裤、轻薄T恤需求提升"
        },
        {
          "date": "2026-06-12",
          "code": 81,
          "weather": "阵雨",
          "temp_max": 29.0,
          "temp_min": 24.3,
          "precipitation": 12.6,
          "wind": 12.4,
          "risk_score": 34,
          "signal": "降雨影响客流，防雨、防滑与轻防护品类需关注"
        }
      ],
      "risk_score": 34,
      "signal": "天气整体平稳，户外与亲子活动具备恢复基础"
    },
    "southwest": {
      "name": "西南",
      "city": "Chengdu",
      "days": [
        {
          "date": "2026-06-10",
          "code": 3,
          "weather": "阴",
          "temp_max": 30.8,
          "temp_min": 20.1,
          "precipitation": 0.0,
          "wind": 11.6,
          "risk_score": 20,
          "signal": "气温偏高，防晒、短裤、轻薄T恤需求提升"
        },
        {
          "date": "2026-06-11",
          "code": 53,
          "weather": "小雨",
          "temp_max": 31.0,
          "temp_min": 21.9,
          "precipitation": 1.5,
          "wind": 13.1,
          "risk_score": 20,
          "signal": "气温偏高，防晒、短裤、轻薄T恤需求提升"
        },
        {
          "date": "2026-06-12",
          "code": 53,
          "weather": "小雨",
          "temp_max": 29.0,
          "temp_min": 20.5,
          "precipitation": 1.9,
          "wind": 7.8,
          "risk_score": 0,
          "signal": "天气整体平稳，户外与亲子活动具备恢复基础"
        }
      ],
      "risk_score": 20,
      "signal": "气温偏高，防晒、短裤、轻薄T恤需求提升"
    },
    "northwest": {
      "name": "西北",
      "city": "Xi'an",
      "days": [
        {
          "date": "2026-06-10",
          "code": 3,
          "weather": "阴",
          "temp_max": 33.2,
          "temp_min": 19.9,
          "precipitation": 0.0,
          "wind": 12.4,
          "risk_score": 20,
          "signal": "气温偏高，防晒、短裤、轻薄T恤需求提升"
        },
        {
          "date": "2026-06-11",
          "code": 3,
          "weather": "阴",
          "temp_max": 35.5,
          "temp_min": 18.9,
          "precipitation": 0.0,
          "wind": 12.4,
          "risk_score": 35,
          "signal": "高温天气明显，防晒、凉感、速干品类进入主推窗口"
        },
        {
          "date": "2026-06-12",
          "code": 3,
          "weather": "阴",
          "temp_max": 34.5,
          "temp_min": 24.1,
          "precipitation": 0.0,
          "wind": 14.1,
          "risk_score": 20,
          "signal": "气温偏高，防晒、短裤、轻薄T恤需求提升"
        }
      ],
      "risk_score": 35,
      "signal": "气温偏高，防晒、短裤、轻薄T恤需求提升"
    }
  }
}